LICENSE
MANIFEST.in
README.md
setup.cfg
setup.py
ngender/__init__.py
ngender/charfreq.csv
ngender/cli.py
ngender/ngender.py
ngender.egg-info/PKG-INFO
ngender.egg-info/SOURCES.txt
ngender.egg-info/dependency_links.txt
ngender.egg-info/entry_points.txt
ngender.egg-info/top_level.txt