Metadata-Version: 1.1
Name: ngender
Version: 0.1.0
Summary: Guess gender for Chinese names
Home-page: https://github.com/observerss/ngender
Author: Jingchao Hu(observerss)
Author-email: jingchaohu@gmail.com
License: The MIT License (MIT)
